{
  "book": 10,
  "card": 13,
  "lineStart": 241,
  "lineEnd": 260,
  "lines": [
    {
      "n": 241,
      "greek": "ὣς οἱ μὲν κλαίοντες ἐέρχατο, τοῖσι δὲ Κίρκη"
    },
    {
      "n": 242,
      "greek": "πάρ ῥʼ ἄκυλον βάλανόν τε βάλεν καρπόν τε κρανείης"
    },
    {
      "n": 243,
      "greek": "ἔδμεναι, οἷα σύες χαμαιευνάδες αἰὲν ἔδουσιν."
    },
    {
      "n": 244,
      "greek": "Εὐρύλοχος δʼ αἶψʼ ἦλθε θοὴν ἐπὶ νῆα μέλαιναν"
    },
    {
      "n": 245,
      "greek": "ἀγγελίην ἑτάρων ἐρέων καὶ ἀδευκέα πότμον."
    },
    {
      "n": 246,
      "greek": "οὐδέ τι ἐκφάσθαι δύνατο ἔπος ἱέμενός περ,"
    },
    {
      "n": 247,
      "greek": "κῆρ ἄχεϊ μεγάλῳ βεβολημένος· ἐν δέ οἱ ὄσσε"
    },
    {
      "n": 248,
      "greek": "δακρυόφιν πίμπλαντο, γόον δʼ ὠίετο θυμός."
    },
    {
      "n": 249,
      "greek": "ἀλλʼ ὅτε δή μιν πάντες ἀγασσάμεθʼ ἐξερέοντες,"
    },
    {
      "n": 250,
      "greek": "καὶ τότε τῶν ἄλλων ἑτάρων κατέλεξεν ὄλεθρον·"
    },
    {
      "n": 251,
      "greek": "ἤιομεν, ὡς ἐκέλευες, ἀνὰ δρυμά, φαίδιμʼ Ὀδυσσεῦ·"
    },
    {
      "n": 252,
      "greek": "εὕρομεν ἐν βήσσῃσι τετυγμένα δώματα καλὰ"
    },
    {
      "n": 253,
      "greek": "ξεστοῖσιν λάεσσι, περισκέπτῳ ἐνὶ χώρῳ."
    },
    {
      "n": 254,
      "greek": "ἔνθα δέ τις μέγαν ἱστὸν ἐποιχομένη λίγʼ ἄειδεν,"
    },
    {
      "n": 255,
      "greek": "ἢ θεὸς ἠὲ γυνή· τοὶ δὲ φθέγγοντο καλεῦντες."
    },
    {
      "n": 256,
      "greek": "ἡ δʼ αἶψʼ ἐξελθοῦσα θύρας ὤιξε φαεινὰς"
    },
    {
      "n": 257,
      "greek": "καὶ κάλει· οἱ δʼ ἅμα πάντες ἀιδρείῃσιν ἕποντο·"
    },
    {
      "n": 258,
      "greek": "αὐτὰρ ἐγὼν ὑπέμεινα, ὀισάμενος δόλον εἶναι."
    },
    {
      "n": 259,
      "greek": "οἱ δʼ ἅμʼ ἀιστώθησαν ἀολλέες, οὐδέ τις αὐτῶν"
    },
    {
      "n": 260,
      "greek": "ἐξεφάνη· δηρὸν δὲ καθήμενος ἐσκοπίαζον."
    }
  ],
  "translations": null,
  "meta": {
    "source": "urn:cts:greekLit:tlg0012.tlg002.perseus-grc2"
  },
  "murray": [
    {
      "lines": [
        245,
        249
      ],
      "text": "to bring tiding of his comrades and their shameful doom. Not a word could he utter, for all his desire, so stricken to the heart was he with great distress, and his eyes were filled with tears, and his spirit was set on lamentation. But when we questioned him in amazement,"
    },
    {
      "lines": [
        250,
        254
      ],
      "text": "then he told the fate of the others, his comrades. “‘We went through the thickets, as thou badest, noble Odysseus. We found in the forest glades a fair palace, built of polished stones, in a place of wide outlook. There someone was going to and fro before a great web, and singing with clear voice,"
    },
    {
      "lines": [
        255,
        259
      ],
      "text": "some goddess or some woman, and they cried aloud, and called to her. And she came forth straightway, and opened the bright doors, and bade them in; and they all went with her in their folly. But I remained behind, for I suspected that there was a snare. Then they all vanished together, nor did one of them"
    },
    {
      "lines": [
        260,
        260
      ],
      "text": "appear again, though I sat long and watched.’ “So he spoke, and I cast my silver-studded sword about my shoulders, a great sword of bronze, and slung my bow about me, and bade him lead me back by the self-same road. But he clasped me with both hands, and be sought me by my knees,"
    }
  ]
}
